quakeio/__init__.py
quakeio/__main__.py
quakeio/brace2.mplstyle
quakeio/core.py
quakeio/elcentro.py
quakeio/obs.py
quakeio/processing.py
quakeio/svg.py
quakeio/vega.py
quakeio/utils/__init__.py
quakeio/utils/parseutils.py
quakeio/utils/processing.py
quakeio/utils/spectrum.py
quakeio-0.1.20.dist-info/METADATA
quakeio-0.1.20.dist-info/WHEEL
quakeio-0.1.20.dist-info/entry_points.txt
quakeio-0.1.20.dist-info/top_level.txt
quakeio-0.1.20.dist-info/RECORD
