Metadata-Version: 2.1
Name: quakeio
Version: 0.1.20
Summary: quakeio
Home-page: https://github.com/claudioperez/quakeio
Author: Claudio M. Perez
Author-email: claudio_perez@berkeley.edu
Keywords: seismic,earthquake,parser
Classifier: Development Status :: 5 - Production/Stable
Classifier: Intended Audience :: Developers
Classifier: License :: OSI Approved :: BSD License
Classifier: Programming Language :: Python :: 3
Classifier: Programming Language :: Python :: 3 :: Only
Requires-Python: >=3.6
Requires-Dist: pyyaml
Requires-Dist: numpy <1.20.0 ; python_version < "3.8"
Requires-Dist: scipy <1.6.0 ; python_version == "3.6"
Requires-Dist: scipy <1.8 ; python_version == "3.7"
Requires-Dist: numpy <1.25.0 ; python_version == "3.8"
Requires-Dist: scipy >1.6.0 ; python_version > "3.7"
Requires-Dist: numpy ; python_version >= "3.9"
Provides-Extra: docs
Requires-Dist: sphinx ; extra == 'docs'
Requires-Dist: jaraco.packaging >=8.2 ; extra == 'docs'
Requires-Dist: rst.linker >=1.9 ; extra == 'docs'
Provides-Extra: plots
Requires-Dist: matplotlib ; extra == 'plots'
Provides-Extra: testing
Requires-Dist: pytest >=4.6 ; extra == 'testing'
Requires-Dist: pytest-checkdocs >=2.4 ; extra == 'testing'
Requires-Dist: pytest-flake8 ; extra == 'testing'
Requires-Dist: pytest-cov ; extra == 'testing'
Requires-Dist: pytest-enabler >=1.0.1 ; extra == 'testing'
Requires-Dist: pandas ; extra == 'testing'
Requires-Dist: pytest-black >=0.3.7 ; (platform_python_implementation != "PyPy" and python_version < "3.10") and extra == 'testing'
Requires-Dist: pytest-mypy ; (platform_python_implementation != "PyPy" and python_version < "3.10") and extra == 'testing'
